{
    "blower01run": 1,
    "blower02run": 1,
    "blower03run": 1,
    "blower01fault": 0,
    "blower02fault": 0,
    "blower03fault": 0,
    "blower01control": 1,
    "blower02control": 1,
    "blower03control": 1,
    "blower01customcycle": 1,
    "blower02customcycle": 1,
    "blower03customcycle": 1,
    "blower01cycle": 1,
    "blower02cycle": 1,
    "blower03cycle": 1,
    "blower01cycleofftime": 1,
    "blower02cycleofftime": 1,
    "blower03cycleofftime": 1,
    "blower01cycleontime": 1,
    "blower02cycleontime": 1,
    "blower03cycleontime": 1,
    "blower01override": 0,
    "blower02override": 0,
    "blower03override": 0,
    "zone01temp": 114.00,
    "zone02temp": 115.00,
    "zone03temp": 116.00,
    "zone01lvtemp": 100.20,
    "zone02lvtemp": 102.00,
    "zone03lvtemp": 104.00,
    "zone01avgtemp": 114.00,
    "zone02avgtemp": 115.00,
    "zone03avgtemp": 116.00,
    "zone01pfrptime": 0,
    "zone02pfrptime": 0,
    "zone03pfrptime": 0,
    "zone01moveto": 0,
    "zone02moveto": 0,
    "zone03moveto": 0,
    "zone01control": 1,
    "zone02control": 0,
    "zone03control": 1,
    "zone01regime": 1,
    "zone02regime": 2,
    "zone03regime": 3,
    "zone01regtimer": 300,
    "zone02regtimer": 300,
    "zone03regtimer": 300,
    "zone01reset": 1,
    "zone02reset": 0,
    "zone03reset": 1,
    "zone01print": 1,
    "zone02print": 1,
    "zone03print": 1,
    "zone01avgtimer": 0,
    "zone02avgtimer": 0,
    "zone03avgtimer": 0,
    "batchfilesinuse": 0,
    "blowerstartupinuse": 0,
    "settingsinuse": 0,
    "zonestartupinuse": 0,
    "refreshsettings": 0,
    "time": "06-05-2017 06:26:20"
}
